{
  "collectionName": "components_common_blocks_headers",
  "info": {
    "displayName": "header",
    "icon": "apps"
  },
  "options": {},
  "attributes": {
    "background_image": {
      "type": "media",
      "multiple": false,
      "allowedTypes": [
        "images"
      ]
    },
    "title": {
      "type": "string",
      "required": true
    },
    "description": {
      "type": "text",
      "required": false
    },
    "primary_button_text": {
      "type": "string",
      "required": true
    },
    "primary_button_link": {
      "type": "string",
      "required": true
    }
  },
  "config": {}
}
